{
  "schemaVersion": 4,
  "generatedAt": "2026-03-27T06:28:13.255Z",
  "instrument": "金 / XAUUSD",
  "artifacts": {
    "metricsSchemaVersion": 4,
    "predictionSchemaVersion": 4,
    "forecastSchemaVersion": 4
  },
  "provenance": {
    "rawRows": 2834,
    "sourcePath": "/Users/inouehiroshi/Documents/GitHub/SignalCascade/PyTorch/artifacts/gold_xauusd_m30/live/xauusd_m30_latest.csv",
    "start": "2025-12-30T11:00:00.000Z",
    "end": "2026-03-27T05:30:00.000Z"
  },
  "run": {
    "anchorTime": "2026-03-24T20:00:00.000Z",
    "anchorClose": 4455.425,
    "selectedHorizon": 1,
    "selectedHours": 4,
    "position": 0.18051757675864127,
    "overlayAction": "reduce",
    "policyStatus": "active",
    "trainSamples": 129,
    "validationSamples": 32,
    "sampleCount": 164,
    "effectiveSampleCount": 161,
    "purgedSamples": 3,
    "bestValidationLoss": -0.392638826277107,
    "bestEpoch": 6,
    "convergenceGain": 0.18435578234493732,
    "generalizationGap": -0.11153722483693629,
    "sourceRows": 2834,
    "modelDirectory": "/Users/inouehiroshi/Documents/GitHub/SignalCascade/PyTorch/artifacts/gold_xauusd_m30/current",
    "tuningSessionId": "20260327T041009Z",
    "bestParams": {
      "epochs": 6,
      "batchSize": 16,
      "learningRate": 0.0008,
      "hiddenDim": 48,
      "dropout": 0.1,
      "weightDecay": 0.0001
    }
  },
  "chart": {
    "rows": [
      {
        "ts": 1774265400000,
        "label": "2026-03-23T11:30:00.000Z",
        "phase": "history",
        "close": 4378.795,
        "high": 4431.425,
        "low": 4361.115,
        "forecastBase": null,
        "forecastLower": null,
        "forecastUpper": null,
        "forecastSpread": null,
        "actualClose": null,
        "actualRangeStart": null,
        "actualRangeEnd": null
      },
      {
        "ts": 1774267200000,
        "label": "2026-03-23T12:00:00.000Z",
        "phase": "history",
        "close": 4389.855,
        "high": 4404.725,
        "low": 4336.305,
        "forecastBase": null,
        "forecastLower": null,
        "forecastUpper": null,
        "forecastSpread": null,
        "actualClose": null,
        "actualRangeStart": null,
        "actualRangeEnd": null
      },
      {
        "ts": 1774269000000,
        "label": "2026-03-23T12:30:00.000Z",
        "phase": "history",
        "close": 4478.095,
        "high": 4492.185,
        "low": 4373.035,
        "forecastBase": null,
        "forecastLower": null,
        "forecastUpper": null,
        "forecastSpread": null,
        "actualClose": null,
        "actualRangeStart": null,
        "actualRangeEnd": null
      },
      {
        "ts": 1774270800000,
        "label": "2026-03-23T13:00:00.000Z",
        "phase": "history",
        "close": 4409.045,
        "high": 4484.905,
        "low": 4405.008,
        "forecastBase": null,
        "forecastLower": null,
        "forecastUpper": null,
        "forecastSpread": null,
        "actualClose": null,
        "actualRangeStart": null,
        "actualRangeEnd": null
      },
      {
        "ts": 1774272600000,
        "label": "2026-03-23T13:30:00.000Z",
        "phase": "history",
        "close": 4453.975,
        "high": 4466.315,
        "low": 4400.995,
        "forecastBase": null,
        "forecastLower": null,
        "forecastUpper": null,
        "forecastSpread": null,
        "actualClose": null,
        "actualRangeStart": null,
        "actualRangeEnd": null
      },
      {
        "ts": 1774274400000,
        "label": "2026-03-23T14:00:00.000Z",
        "phase": "history",
        "close": 4486.225,
        "high": 4512.665,
        "low": 4453.385,
        "forecastBase": null,
        "forecastLower": null,
        "forecastUpper": null,
        "forecastSpread": null,
        "actualClose": null,
        "actualRangeStart": null,
        "actualRangeEnd": null
      },
      {
        "ts": 1774276200000,
        "label": "2026-03-23T14:30:00.000Z",
        "phase": "history",
        "close": 4461.695,
        "high": 4504.145,
        "low": 4456.565,
        "forecastBase": null,
        "forecastLower": null,
        "forecastUpper": null,
        "forecastSpread": null,
        "actualClose": null,
        "actualRangeStart": null,
        "actualRangeEnd": null
      },
      {
        "ts": 1774278000000,
        "label": "2026-03-23T15:00:00.000Z",
        "phase": "history",
        "close": 4447.355,
        "high": 4486.765,
        "low": 4426.988,
        "forecastBase": null,
        "forecastLower": null,
        "forecastUpper": null,
        "forecastSpread": null,
        "actualClose": null,
        "actualRangeStart": null,
        "actualRangeEnd": null
      },
      {
        "ts": 1774279800000,
        "label": "2026-03-23T15:30:00.000Z",
        "phase": "history",
        "close": 4363.515,
        "high": 4455.775,
        "low": 4350.798,
        "forecastBase": null,
        "forecastLower": null,
        "forecastUpper": null,
        "forecastSpread": null,
        "actualClose": null,
        "actualRangeStart": null,
        "actualRangeEnd": null
      },
      {
        "ts": 1774281600000,
        "label": "2026-03-23T16:00:00.000Z",
        "phase": "history",
        "close": 4354.458,
        "high": 4389.885,
        "low": 4352.058,
        "forecastBase": null,
        "forecastLower": null,
        "forecastUpper": null,
        "forecastSpread": null,
        "actualClose": null,
        "actualRangeStart": null,
        "actualRangeEnd": null
      },
      {
        "ts": 1774283400000,
        "label": "2026-03-23T16:30:00.000Z",
        "phase": "history",
        "close": 4375.325,
        "high": 4391.505,
        "low": 4353.258,
        "forecastBase": null,
        "forecastLower": null,
        "forecastUpper": null,
        "forecastSpread": null,
        "actualClose": null,
        "actualRangeStart": null,
        "actualRangeEnd": null
      },
      {
        "ts": 1774285200000,
        "label": "2026-03-23T17:00:00.000Z",
        "phase": "history",
        "close": 4405.275,
        "high": 4413.615,
        "low": 4370.575,
        "forecastBase": null,
        "forecastLower": null,
        "forecastUpper": null,
        "forecastSpread": null,
        "actualClose": null,
        "actualRangeStart": null,
        "actualRangeEnd": null
      },
      {
        "ts": 1774287000000,
        "label": "2026-03-23T17:30:00.000Z",
        "phase": "history",
        "close": 4425.965,
        "high": 4438.835,
        "low": 4403.875,
        "forecastBase": null,
        "forecastLower": null,
        "forecastUpper": null,
        "forecastSpread": null,
        "actualClose": null,
        "actualRangeStart": null,
        "actualRangeEnd": null
      },
      {
        "ts": 1774288800000,
        "label": "2026-03-23T18:00:00.000Z",
        "phase": "history",
        "close": 4425.895,
        "high": 4430.515,
        "low": 4402.005,
        "forecastBase": null,
        "forecastLower": null,
        "forecastUpper": null,
        "forecastSpread": null,
        "actualClose": null,
        "actualRangeStart": null,
        "actualRangeEnd": null
      },
      {
        "ts": 1774290600000,
        "label": "2026-03-23T18:30:00.000Z",
        "phase": "history",
        "close": 4448.785,
        "high": 4466.895,
        "low": 4425.365,
        "forecastBase": null,
        "forecastLower": null,
        "forecastUpper": null,
        "forecastSpread": null,
        "actualClose": null,
        "actualRangeStart": null,
        "actualRangeEnd": null
      },
      {
        "ts": 1774292400000,
        "label": "2026-03-23T19:00:00.000Z",
        "phase": "history",
        "close": 4410.445,
        "high": 4450.325,
        "low": 4392.885,
        "forecastBase": null,
        "forecastLower": null,
        "forecastUpper": null,
        "forecastSpread": null,
        "actualClose": null,
        "actualRangeStart": null,
        "actualRangeEnd": null
      },
      {
        "ts": 1774294200000,
        "label": "2026-03-23T19:30:00.000Z",
        "phase": "history",
        "close": 4398.025,
        "high": 4427.425,
        "low": 4396.825,
        "forecastBase": null,
        "forecastLower": null,
        "forecastUpper": null,
        "forecastSpread": null,
        "actualClose": null,
        "actualRangeStart": null,
        "actualRangeEnd": null
      },
      {
        "ts": 1774296000000,
        "label": "2026-03-23T20:00:00.000Z",
        "phase": "history",
        "close": 4406.965,
        "high": 4412.975,
        "low": 4382.575,
        "forecastBase": null,
        "forecastLower": null,
        "forecastUpper": null,
        "forecastSpread": null,
        "actualClose": null,
        "actualRangeStart": null,
        "actualRangeEnd": null
      },
      {
        "ts": 1774297800000,
        "label": "2026-03-23T20:30:00.000Z",
        "phase": "history",
        "close": 4405.895,
        "high": 4412.635,
        "low": 4395.655,
        "forecastBase": null,
        "forecastLower": null,
        "forecastUpper": null,
        "forecastSpread": null,
        "actualClose": null,
        "actualRangeStart": null,
        "actualRangeEnd": null
      },
      {
        "ts": 1774303200000,
        "label": "2026-03-23T22:00:00.000Z",
        "phase": "history",
        "close": 4413.835,
        "high": 4419.598,
        "low": 4359.348,
        "forecastBase": null,
        "forecastLower": null,
        "forecastUpper": null,
        "forecastSpread": null,
        "actualClose": null,
        "actualRangeStart": null,
        "actualRangeEnd": null
      },
      {
        "ts": 1774305000000,
        "label": "2026-03-23T22:30:00.000Z",
        "phase": "history",
        "close": 4426.338,
        "high": 4431.065,
        "low": 4397.975,
        "forecastBase": null,
        "forecastLower": null,
        "forecastUpper": null,
        "forecastSpread": null,
        "actualClose": null,
        "actualRangeStart": null,
        "actualRangeEnd": null
      },
      {
        "ts": 1774306800000,
        "label": "2026-03-23T23:00:00.000Z",
        "phase": "history",
        "close": 4441.525,
        "high": 4448.005,
        "low": 4422.798,
        "forecastBase": null,
        "forecastLower": null,
        "forecastUpper": null,
        "forecastSpread": null,
        "actualClose": null,
        "actualRangeStart": null,
        "actualRangeEnd": null
      },
      {
        "ts": 1774308600000,
        "label": "2026-03-23T23:30:00.000Z",
        "phase": "history",
        "close": 4440.915,
        "high": 4446.075,
        "low": 4421.705,
        "forecastBase": null,
        "forecastLower": null,
        "forecastUpper": null,
        "forecastSpread": null,
        "actualClose": null,
        "actualRangeStart": null,
        "actualRangeEnd": null
      },
      {
        "ts": 1774310400000,
        "label": "2026-03-24T00:00:00.000Z",
        "phase": "history",
        "close": 4377.705,
        "high": 4446.435,
        "low": 4367.828,
        "forecastBase": null,
        "forecastLower": null,
        "forecastUpper": null,
        "forecastSpread": null,
        "actualClose": null,
        "actualRangeStart": null,
        "actualRangeEnd": null
      },
      {
        "ts": 1774312200000,
        "label": "2026-03-24T00:30:00.000Z",
        "phase": "history",
        "close": 4364.035,
        "high": 4387.045,
        "low": 4330.695,
        "forecastBase": null,
        "forecastLower": null,
        "forecastUpper": null,
        "forecastSpread": null,
        "actualClose": null,
        "actualRangeStart": null,
        "actualRangeEnd": null
      },
      {
        "ts": 1774314000000,
        "label": "2026-03-24T01:00:00.000Z",
        "phase": "history",
        "close": 4354.365,
        "high": 4373.895,
        "low": 4327.825,
        "forecastBase": null,
        "forecastLower": null,
        "forecastUpper": null,
        "forecastSpread": null,
        "actualClose": null,
        "actualRangeStart": null,
        "actualRangeEnd": null
      },
      {
        "ts": 1774315800000,
        "label": "2026-03-24T01:30:00.000Z",
        "phase": "history",
        "close": 4321.765,
        "high": 4368.225,
        "low": 4307.555,
        "forecastBase": null,
        "forecastLower": null,
        "forecastUpper": null,
        "forecastSpread": null,
        "actualClose": null,
        "actualRangeStart": null,
        "actualRangeEnd": null
      },
      {
        "ts": 1774317600000,
        "label": "2026-03-24T02:00:00.000Z",
        "phase": "history",
        "close": 4351.575,
        "high": 4353.395,
        "low": 4305.565,
        "forecastBase": null,
        "forecastLower": null,
        "forecastUpper": null,
        "forecastSpread": null,
        "actualClose": null,
        "actualRangeStart": null,
        "actualRangeEnd": null
      },
      {
        "ts": 1774319400000,
        "label": "2026-03-24T02:30:00.000Z",
        "phase": "history",
        "close": 4365.725,
        "high": 4378.965,
        "low": 4344.165,
        "forecastBase": null,
        "forecastLower": null,
        "forecastUpper": null,
        "forecastSpread": null,
        "actualClose": null,
        "actualRangeStart": null,
        "actualRangeEnd": null
      },
      {
        "ts": 1774321200000,
        "label": "2026-03-24T03:00:00.000Z",
        "phase": "history",
        "close": 4364.365,
        "high": 4367.905,
        "low": 4349.835,
        "forecastBase": null,
        "forecastLower": null,
        "forecastUpper": null,
        "forecastSpread": null,
        "actualClose": null,
        "actualRangeStart": null,
        "actualRangeEnd": null
      },
      {
        "ts": 1774323000000,
        "label": "2026-03-24T03:30:00.000Z",
        "phase": "history",
        "close": 4347.045,
        "high": 4364.465,
        "low": 4334.835,
        "forecastBase": null,
        "forecastLower": null,
        "forecastUpper": null,
        "forecastSpread": null,
        "actualClose": null,
        "actualRangeStart": null,
        "actualRangeEnd": null
      },
      {
        "ts": 1774324800000,
        "label": "2026-03-24T04:00:00.000Z",
        "phase": "history",
        "close": 4339.485,
        "high": 4357.005,
        "low": 4326.245,
        "forecastBase": null,
        "forecastLower": null,
        "forecastUpper": null,
        "forecastSpread": null,
        "actualClose": null,
        "actualRangeStart": null,
        "actualRangeEnd": null
      },
      {
        "ts": 1774326600000,
        "label": "2026-03-24T04:30:00.000Z",
        "phase": "history",
        "close": 4333.115,
        "high": 4349.015,
        "low": 4331.775,
        "forecastBase": null,
        "forecastLower": null,
        "forecastUpper": null,
        "forecastSpread": null,
        "actualClose": null,
        "actualRangeStart": null,
        "actualRangeEnd": null
      },
      {
        "ts": 1774328400000,
        "label": "2026-03-24T05:00:00.000Z",
        "phase": "history",
        "close": 4334.915,
        "high": 4346.285,
        "low": 4319.515,
        "forecastBase": null,
        "forecastLower": null,
        "forecastUpper": null,
        "forecastSpread": null,
        "actualClose": null,
        "actualRangeStart": null,
        "actualRangeEnd": null
      },
      {
        "ts": 1774330200000,
        "label": "2026-03-24T05:30:00.000Z",
        "phase": "history",
        "close": 4346.945,
        "high": 4373.595,
        "low": 4320.645,
        "forecastBase": null,
        "forecastLower": null,
        "forecastUpper": null,
        "forecastSpread": null,
        "actualClose": null,
        "actualRangeStart": null,
        "actualRangeEnd": null
      },
      {
        "ts": 1774332000000,
        "label": "2026-03-24T06:00:00.000Z",
        "phase": "history",
        "close": 4386.595,
        "high": 4396.455,
        "low": 4342.635,
        "forecastBase": null,
        "forecastLower": null,
        "forecastUpper": null,
        "forecastSpread": null,
        "actualClose": null,
        "actualRangeStart": null,
        "actualRangeEnd": null
      },
      {
        "ts": 1774333800000,
        "label": "2026-03-24T06:30:00.000Z",
        "phase": "history",
        "close": 4401.855,
        "high": 4404.765,
        "low": 4372.525,
        "forecastBase": null,
        "forecastLower": null,
        "forecastUpper": null,
        "forecastSpread": null,
        "actualClose": null,
        "actualRangeStart": null,
        "actualRangeEnd": null
      },
      {
        "ts": 1774335600000,
        "label": "2026-03-24T07:00:00.000Z",
        "phase": "history",
        "close": 4412.115,
        "high": 4425.218,
        "low": 4399.365,
        "forecastBase": null,
        "forecastLower": null,
        "forecastUpper": null,
        "forecastSpread": null,
        "actualClose": null,
        "actualRangeStart": null,
        "actualRangeEnd": null
      },
      {
        "ts": 1774337400000,
        "label": "2026-03-24T07:30:00.000Z",
        "phase": "history",
        "close": 4416.855,
        "high": 4432.785,
        "low": 4399.555,
        "forecastBase": null,
        "forecastLower": null,
        "forecastUpper": null,
        "forecastSpread": null,
        "actualClose": null,
        "actualRangeStart": null,
        "actualRangeEnd": null
      },
      {
        "ts": 1774339200000,
        "label": "2026-03-24T08:00:00.000Z",
        "phase": "history",
        "close": 4396.295,
        "high": 4420.735,
        "low": 4390.895,
        "forecastBase": null,
        "forecastLower": null,
        "forecastUpper": null,
        "forecastSpread": null,
        "actualClose": null,
        "actualRangeStart": null,
        "actualRangeEnd": null
      },
      {
        "ts": 1774341000000,
        "label": "2026-03-24T08:30:00.000Z",
        "phase": "history",
        "close": 4411.535,
        "high": 4414.285,
        "low": 4391.305,
        "forecastBase": null,
        "forecastLower": null,
        "forecastUpper": null,
        "forecastSpread": null,
        "actualClose": null,
        "actualRangeStart": null,
        "actualRangeEnd": null
      },
      {
        "ts": 1774342800000,
        "label": "2026-03-24T09:00:00.000Z",
        "phase": "history",
        "close": 4407.085,
        "high": 4419.035,
        "low": 4395.625,
        "forecastBase": null,
        "forecastLower": null,
        "forecastUpper": null,
        "forecastSpread": null,
        "actualClose": null,
        "actualRangeStart": null,
        "actualRangeEnd": null
      },
      {
        "ts": 1774344600000,
        "label": "2026-03-24T09:30:00.000Z",
        "phase": "history",
        "close": 4425.945,
        "high": 4430.625,
        "low": 4404.915,
        "forecastBase": null,
        "forecastLower": null,
        "forecastUpper": null,
        "forecastSpread": null,
        "actualClose": null,
        "actualRangeStart": null,
        "actualRangeEnd": null
      },
      {
        "ts": 1774346400000,
        "label": "2026-03-24T10:00:00.000Z",
        "phase": "history",
        "close": 4421.905,
        "high": 4432.865,
        "low": 4414.705,
        "forecastBase": null,
        "forecastLower": null,
        "forecastUpper": null,
        "forecastSpread": null,
        "actualClose": null,
        "actualRangeStart": null,
        "actualRangeEnd": null
      },
      {
        "ts": 1774348200000,
        "label": "2026-03-24T10:30:00.000Z",
        "phase": "history",
        "close": 4438.445,
        "high": 4441.308,
        "low": 4414.355,
        "forecastBase": null,
        "forecastLower": null,
        "forecastUpper": null,
        "forecastSpread": null,
        "actualClose": null,
        "actualRangeStart": null,
        "actualRangeEnd": null
      },
      {
        "ts": 1774350000000,
        "label": "2026-03-24T11:00:00.000Z",
        "phase": "history",
        "close": 4412.775,
        "high": 4441.865,
        "low": 4373.048,
        "forecastBase": null,
        "forecastLower": null,
        "forecastUpper": null,
        "forecastSpread": null,
        "actualClose": null,
        "actualRangeStart": null,
        "actualRangeEnd": null
      },
      {
        "ts": 1774351800000,
        "label": "2026-03-24T11:30:00.000Z",
        "phase": "history",
        "close": 4407.345,
        "high": 4431.475,
        "low": 4390.175,
        "forecastBase": null,
        "forecastLower": null,
        "forecastUpper": null,
        "forecastSpread": null,
        "actualClose": null,
        "actualRangeStart": null,
        "actualRangeEnd": null
      },
      {
        "ts": 1774353600000,
        "label": "2026-03-24T12:00:00.000Z",
        "phase": "history",
        "close": 4401.995,
        "high": 4427.205,
        "low": 4395.088,
        "forecastBase": null,
        "forecastLower": null,
        "forecastUpper": null,
        "forecastSpread": null,
        "actualClose": null,
        "actualRangeStart": null,
        "actualRangeEnd": null
      },
      {
        "ts": 1774355400000,
        "label": "2026-03-24T12:30:00.000Z",
        "phase": "history",
        "close": 4378.905,
        "high": 4406.455,
        "low": 4361.545,
        "forecastBase": null,
        "forecastLower": null,
        "forecastUpper": null,
        "forecastSpread": null,
        "actualClose": null,
        "actualRangeStart": null,
        "actualRangeEnd": null
      },
      {
        "ts": 1774357200000,
        "label": "2026-03-24T13:00:00.000Z",
        "phase": "history",
        "close": 4356.808,
        "high": 4389.575,
        "low": 4356.288,
        "forecastBase": null,
        "forecastLower": null,
        "forecastUpper": null,
        "forecastSpread": null,
        "actualClose": null,
        "actualRangeStart": null,
        "actualRangeEnd": null
      },
      {
        "ts": 1774359000000,
        "label": "2026-03-24T13:30:00.000Z",
        "phase": "history",
        "close": 4381.165,
        "high": 4383.058,
        "low": 4350.838,
        "forecastBase": null,
        "forecastLower": null,
        "forecastUpper": null,
        "forecastSpread": null,
        "actualClose": null,
        "actualRangeStart": null,
        "actualRangeEnd": null
      },
      {
        "ts": 1774360800000,
        "label": "2026-03-24T14:00:00.000Z",
        "phase": "history",
        "close": 4408.735,
        "high": 4414.475,
        "low": 4380.019,
        "forecastBase": null,
        "forecastLower": null,
        "forecastUpper": null,
        "forecastSpread": null,
        "actualClose": null,
        "actualRangeStart": null,
        "actualRangeEnd": null
      },
      {
        "ts": 1774362600000,
        "label": "2026-03-24T14:30:00.000Z",
        "phase": "history",
        "close": 4415.558,
        "high": 4433.085,
        "low": 4399.748,
        "forecastBase": null,
        "forecastLower": null,
        "forecastUpper": null,
        "forecastSpread": null,
        "actualClose": null,
        "actualRangeStart": null,
        "actualRangeEnd": null
      },
      {
        "ts": 1774364400000,
        "label": "2026-03-24T15:00:00.000Z",
        "phase": "history",
        "close": 4412.298,
        "high": 4420.055,
        "low": 4395.758,
        "forecastBase": null,
        "forecastLower": null,
        "forecastUpper": null,
        "forecastSpread": null,
        "actualClose": null,
        "actualRangeStart": null,
        "actualRangeEnd": null
      },
      {
        "ts": 1774366200000,
        "label": "2026-03-24T15:30:00.000Z",
        "phase": "history",
        "close": 4411.118,
        "high": 4430.398,
        "low": 4408.835,
        "forecastBase": null,
        "forecastLower": null,
        "forecastUpper": null,
        "forecastSpread": null,
        "actualClose": null,
        "actualRangeStart": null,
        "actualRangeEnd": null
      },
      {
        "ts": 1774368000000,
        "label": "2026-03-24T16:00:00.000Z",
        "phase": "history",
        "close": 4420.698,
        "high": 4425.268,
        "low": 4402.198,
        "forecastBase": null,
        "forecastLower": null,
        "forecastUpper": null,
        "forecastSpread": null,
        "actualClose": null,
        "actualRangeStart": null,
        "actualRangeEnd": null
      },
      {
        "ts": 1774369800000,
        "label": "2026-03-24T16:30:00.000Z",
        "phase": "history",
        "close": 4420.958,
        "high": 4427.148,
        "low": 4408.288,
        "forecastBase": null,
        "forecastLower": null,
        "forecastUpper": null,
        "forecastSpread": null,
        "actualClose": null,
        "actualRangeStart": null,
        "actualRangeEnd": null
      },
      {
        "ts": 1774371600000,
        "label": "2026-03-24T17:00:00.000Z",
        "phase": "history",
        "close": 4399.838,
        "high": 4426.058,
        "low": 4387.975,
        "forecastBase": null,
        "forecastLower": null,
        "forecastUpper": null,
        "forecastSpread": null,
        "actualClose": null,
        "actualRangeStart": null,
        "actualRangeEnd": null
      },
      {
        "ts": 1774373400000,
        "label": "2026-03-24T17:30:00.000Z",
        "phase": "history",
        "close": 4388.395,
        "high": 4399.838,
        "low": 4372.155,
        "forecastBase": null,
        "forecastLower": null,
        "forecastUpper": null,
        "forecastSpread": null,
        "actualClose": null,
        "actualRangeStart": null,
        "actualRangeEnd": null
      },
      {
        "ts": 1774375200000,
        "label": "2026-03-24T18:00:00.000Z",
        "phase": "history",
        "close": 4406.975,
        "high": 4409.585,
        "low": 4383.545,
        "forecastBase": null,
        "forecastLower": null,
        "forecastUpper": null,
        "forecastSpread": null,
        "actualClose": null,
        "actualRangeStart": null,
        "actualRangeEnd": null
      },
      {
        "ts": 1774377000000,
        "label": "2026-03-24T18:30:00.000Z",
        "phase": "history",
        "close": 4389.285,
        "high": 4423.105,
        "low": 4383.695,
        "forecastBase": null,
        "forecastLower": null,
        "forecastUpper": null,
        "forecastSpread": null,
        "actualClose": null,
        "actualRangeStart": null,
        "actualRangeEnd": null
      },
      {
        "ts": 1774378800000,
        "label": "2026-03-24T19:00:00.000Z",
        "phase": "history",
        "close": 4407.128,
        "high": 4411.108,
        "low": 4388.475,
        "forecastBase": null,
        "forecastLower": null,
        "forecastUpper": null,
        "forecastSpread": null,
        "actualClose": null,
        "actualRangeStart": null,
        "actualRangeEnd": null
      },
      {
        "ts": 1774380600000,
        "label": "2026-03-24T19:30:00.000Z",
        "phase": "history",
        "close": 4400.085,
        "high": 4407.188,
        "low": 4394.755,
        "forecastBase": null,
        "forecastLower": null,
        "forecastUpper": null,
        "forecastSpread": null,
        "actualClose": null,
        "actualRangeStart": null,
        "actualRangeEnd": null
      },
      {
        "ts": 1774382400000,
        "label": "2026-03-24T20:00:00.000Z",
        "phase": "history",
        "close": 4455.425,
        "high": 4483.945,
        "low": 4397.025,
        "forecastBase": null,
        "forecastLower": null,
        "forecastUpper": null,
        "forecastSpread": null,
        "actualClose": null,
        "actualRangeStart": null,
        "actualRangeEnd": null
      },
      {
        "ts": 1774382400000,
        "label": "2026-03-24T20:00:00.000Z",
        "phase": "forecast",
        "close": null,
        "high": null,
        "low": null,
        "forecastBase": 4455.425,
        "forecastLower": 4455.425,
        "forecastUpper": 4455.425,
        "forecastSpread": 0,
        "actualClose": 4455.425,
        "actualRangeStart": 1774369800000,
        "actualRangeEnd": 1774382400000
      },
      {
        "ts": 1774396800000,
        "label": "2026-03-25T00:00:00.000Z",
        "phase": "forecast",
        "close": null,
        "high": null,
        "low": null,
        "forecastBase": 4577.961999976752,
        "forecastLower": 3849.1851481744857,
        "forecastUpper": 5444.720185302222,
        "forecastSpread": 1595.535037127736,
        "actualClose": 4553.105,
        "actualRangeStart": 1774384200000,
        "actualRangeEnd": 1774396800000
      },
      {
        "ts": 1774411200000,
        "label": "2026-03-25T04:00:00.000Z",
        "phase": "forecast",
        "close": null,
        "high": null,
        "low": null,
        "forecastBase": 4448.189042263309,
        "forecastLower": 3709.9894730210567,
        "forecastUpper": 5333.272749046173,
        "forecastSpread": 1623.2832760251163,
        "actualClose": 4573.985,
        "actualRangeStart": 1774398600000,
        "actualRangeEnd": 1774411200000
      },
      {
        "ts": 1774425600000,
        "label": "2026-03-25T08:00:00.000Z",
        "phase": "forecast",
        "close": null,
        "high": null,
        "low": null,
        "forecastBase": 4322.094800221551,
        "forecastLower": 3575.827444012347,
        "forecastUpper": 5224.1065192847345,
        "forecastSpread": 1648.2790752723877,
        "actualClose": 4565.445,
        "actualRangeStart": 1774413000000,
        "actualRangeEnd": 1774425600000
      }
    ],
    "microRows": [
      {
        "ts": 1774265400000,
        "open": 4398.428,
        "high": 4431.425,
        "low": 4361.115,
        "close": 4378.795
      },
      {
        "ts": 1774267200000,
        "open": 4378.825,
        "high": 4404.725,
        "low": 4336.305,
        "close": 4389.855
      },
      {
        "ts": 1774269000000,
        "open": 4389.295,
        "high": 4492.185,
        "low": 4373.035,
        "close": 4478.095
      },
      {
        "ts": 1774270800000,
        "open": 4478.108,
        "high": 4484.905,
        "low": 4405.008,
        "close": 4409.045
      },
      {
        "ts": 1774272600000,
        "open": 4409.365,
        "high": 4466.315,
        "low": 4400.995,
        "close": 4453.975
      },
      {
        "ts": 1774274400000,
        "open": 4454.145,
        "high": 4512.665,
        "low": 4453.385,
        "close": 4486.225
      },
      {
        "ts": 1774276200000,
        "open": 4486.295,
        "high": 4504.145,
        "low": 4456.565,
        "close": 4461.695
      },
      {
        "ts": 1774278000000,
        "open": 4461.238,
        "high": 4486.765,
        "low": 4426.988,
        "close": 4447.355
      },
      {
        "ts": 1774279800000,
        "open": 4446.925,
        "high": 4455.775,
        "low": 4350.798,
        "close": 4363.515
      },
      {
        "ts": 1774281600000,
        "open": 4363.158,
        "high": 4389.885,
        "low": 4352.058,
        "close": 4354.458
      },
      {
        "ts": 1774283400000,
        "open": 4354.538,
        "high": 4391.505,
        "low": 4353.258,
        "close": 4375.325
      },
      {
        "ts": 1774285200000,
        "open": 4375.285,
        "high": 4413.615,
        "low": 4370.575,
        "close": 4405.275
      },
      {
        "ts": 1774287000000,
        "open": 4404.985,
        "high": 4438.835,
        "low": 4403.875,
        "close": 4425.965
      },
      {
        "ts": 1774288800000,
        "open": 4425.995,
        "high": 4430.515,
        "low": 4402.005,
        "close": 4425.895
      },
      {
        "ts": 1774290600000,
        "open": 4425.775,
        "high": 4466.895,
        "low": 4425.365,
        "close": 4448.785
      },
      {
        "ts": 1774292400000,
        "open": 4448.625,
        "high": 4450.325,
        "low": 4392.885,
        "close": 4410.445
      },
      {
        "ts": 1774294200000,
        "open": 4410.225,
        "high": 4427.425,
        "low": 4396.825,
        "close": 4398.025
      },
      {
        "ts": 1774296000000,
        "open": 4397.625,
        "high": 4412.975,
        "low": 4382.575,
        "close": 4406.965
      },
      {
        "ts": 1774297800000,
        "open": 4406.935,
        "high": 4412.635,
        "low": 4395.655,
        "close": 4405.895
      },
      {
        "ts": 1774303200000,
        "open": 4411.898,
        "high": 4419.598,
        "low": 4359.348,
        "close": 4413.835
      },
      {
        "ts": 1774305000000,
        "open": 4413.975,
        "high": 4431.065,
        "low": 4397.975,
        "close": 4426.338
      },
      {
        "ts": 1774306800000,
        "open": 4424.509,
        "high": 4448.005,
        "low": 4422.798,
        "close": 4441.525
      },
      {
        "ts": 1774308600000,
        "open": 4441.505,
        "high": 4446.075,
        "low": 4421.705,
        "close": 4440.915
      },
      {
        "ts": 1774310400000,
        "open": 4440.895,
        "high": 4446.435,
        "low": 4367.828,
        "close": 4377.705
      },
      {
        "ts": 1774312200000,
        "open": 4378.075,
        "high": 4387.045,
        "low": 4330.695,
        "close": 4364.035
      },
      {
        "ts": 1774314000000,
        "open": 4364.165,
        "high": 4373.895,
        "low": 4327.825,
        "close": 4354.365
      },
      {
        "ts": 1774315800000,
        "open": 4354.305,
        "high": 4368.225,
        "low": 4307.555,
        "close": 4321.765
      },
      {
        "ts": 1774317600000,
        "open": 4321.745,
        "high": 4353.395,
        "low": 4305.565,
        "close": 4351.575
      },
      {
        "ts": 1774319400000,
        "open": 4351.595,
        "high": 4378.965,
        "low": 4344.165,
        "close": 4365.725
      },
      {
        "ts": 1774321200000,
        "open": 4365.655,
        "high": 4367.905,
        "low": 4349.835,
        "close": 4364.365
      },
      {
        "ts": 1774323000000,
        "open": 4364.085,
        "high": 4364.465,
        "low": 4334.835,
        "close": 4347.045
      },
      {
        "ts": 1774324800000,
        "open": 4347.025,
        "high": 4357.005,
        "low": 4326.245,
        "close": 4339.485
      },
      {
        "ts": 1774326600000,
        "open": 4339.455,
        "high": 4349.015,
        "low": 4331.775,
        "close": 4333.115
      },
      {
        "ts": 1774328400000,
        "open": 4333.115,
        "high": 4346.285,
        "low": 4319.515,
        "close": 4334.915
      },
      {
        "ts": 1774330200000,
        "open": 4334.595,
        "high": 4373.595,
        "low": 4320.645,
        "close": 4346.945
      },
      {
        "ts": 1774332000000,
        "open": 4347.135,
        "high": 4396.455,
        "low": 4342.635,
        "close": 4386.595
      },
      {
        "ts": 1774333800000,
        "open": 4386.218,
        "high": 4404.765,
        "low": 4372.525,
        "close": 4401.855
      },
      {
        "ts": 1774335600000,
        "open": 4401.885,
        "high": 4425.218,
        "low": 4399.365,
        "close": 4412.115
      },
      {
        "ts": 1774337400000,
        "open": 4412.085,
        "high": 4432.785,
        "low": 4399.555,
        "close": 4416.855
      },
      {
        "ts": 1774339200000,
        "open": 4416.815,
        "high": 4420.735,
        "low": 4390.895,
        "close": 4396.295
      },
      {
        "ts": 1774341000000,
        "open": 4396.008,
        "high": 4414.285,
        "low": 4391.305,
        "close": 4411.535
      },
      {
        "ts": 1774342800000,
        "open": 4412.015,
        "high": 4419.035,
        "low": 4395.625,
        "close": 4407.085
      },
      {
        "ts": 1774344600000,
        "open": 4407.055,
        "high": 4430.625,
        "low": 4404.915,
        "close": 4425.945
      },
      {
        "ts": 1774346400000,
        "open": 4426.255,
        "high": 4432.865,
        "low": 4414.705,
        "close": 4421.905
      },
      {
        "ts": 1774348200000,
        "open": 4421.875,
        "high": 4441.308,
        "low": 4414.355,
        "close": 4438.445
      },
      {
        "ts": 1774350000000,
        "open": 4438.445,
        "high": 4441.865,
        "low": 4373.048,
        "close": 4412.775
      },
      {
        "ts": 1774351800000,
        "open": 4412.605,
        "high": 4431.475,
        "low": 4390.175,
        "close": 4407.345
      },
      {
        "ts": 1774353600000,
        "open": 4407.375,
        "high": 4427.205,
        "low": 4395.088,
        "close": 4401.995
      },
      {
        "ts": 1774355400000,
        "open": 4402.015,
        "high": 4406.455,
        "low": 4361.545,
        "close": 4378.905
      },
      {
        "ts": 1774357200000,
        "open": 4378.885,
        "high": 4389.575,
        "low": 4356.288,
        "close": 4356.808
      },
      {
        "ts": 1774359000000,
        "open": 4356.108,
        "high": 4383.058,
        "low": 4350.838,
        "close": 4381.165
      },
      {
        "ts": 1774360800000,
        "open": 4381.175,
        "high": 4414.475,
        "low": 4380.019,
        "close": 4408.735
      },
      {
        "ts": 1774362600000,
        "open": 4408.555,
        "high": 4433.085,
        "low": 4399.748,
        "close": 4415.558
      },
      {
        "ts": 1774364400000,
        "open": 4415.005,
        "high": 4420.055,
        "low": 4395.758,
        "close": 4412.298
      },
      {
        "ts": 1774366200000,
        "open": 4412.215,
        "high": 4430.398,
        "low": 4408.835,
        "close": 4411.118
      },
      {
        "ts": 1774368000000,
        "open": 4411.158,
        "high": 4425.268,
        "low": 4402.198,
        "close": 4420.698
      },
      {
        "ts": 1774369800000,
        "open": 4420.698,
        "high": 4427.148,
        "low": 4408.288,
        "close": 4420.958
      },
      {
        "ts": 1774371600000,
        "open": 4420.958,
        "high": 4426.058,
        "low": 4387.975,
        "close": 4399.838
      },
      {
        "ts": 1774373400000,
        "open": 4399.838,
        "high": 4399.838,
        "low": 4372.155,
        "close": 4388.395
      },
      {
        "ts": 1774375200000,
        "open": 4388.365,
        "high": 4409.585,
        "low": 4383.545,
        "close": 4406.975
      },
      {
        "ts": 1774377000000,
        "open": 4406.795,
        "high": 4423.105,
        "low": 4383.695,
        "close": 4389.285
      },
      {
        "ts": 1774378800000,
        "open": 4389.275,
        "high": 4411.108,
        "low": 4388.475,
        "close": 4407.128
      },
      {
        "ts": 1774380600000,
        "open": 4407.145,
        "high": 4407.188,
        "low": 4394.755,
        "close": 4400.085
      },
      {
        "ts": 1774382400000,
        "open": 4399.998,
        "high": 4483.945,
        "low": 4397.025,
        "close": 4455.425
      },
      {
        "ts": 1774384200000,
        "open": 4455.395,
        "high": 4481.195,
        "low": 4444.325,
        "close": 4471.835
      },
      {
        "ts": 1774389600000,
        "open": 4471.098,
        "high": 4485.185,
        "low": 4467.715,
        "close": 4469.678
      },
      {
        "ts": 1774391400000,
        "open": 4469.658,
        "high": 4484.198,
        "low": 4455.258,
        "close": 4484.118
      },
      {
        "ts": 1774393200000,
        "open": 4483.778,
        "high": 4509.678,
        "low": 4471.958,
        "close": 4509.548
      },
      {
        "ts": 1774395000000,
        "open": 4509.548,
        "high": 4551.118,
        "low": 4504.035,
        "close": 4546.375
      },
      {
        "ts": 1774396800000,
        "open": 4546.335,
        "high": 4556.618,
        "low": 4537.065,
        "close": 4553.105
      },
      {
        "ts": 1774398600000,
        "open": 4553.105,
        "high": 4571.738,
        "low": 4546.138,
        "close": 4562.698
      },
      {
        "ts": 1774400400000,
        "open": 4562.698,
        "high": 4578.428,
        "low": 4552.085,
        "close": 4575.055
      },
      {
        "ts": 1774402200000,
        "open": 4575.005,
        "high": 4600.955,
        "low": 4573.685,
        "close": 4594.655
      },
      {
        "ts": 1774404000000,
        "open": 4594.635,
        "high": 4596.125,
        "low": 4579.585,
        "close": 4586.635
      },
      {
        "ts": 1774405800000,
        "open": 4586.885,
        "high": 4602.125,
        "low": 4580.695,
        "close": 4583.325
      },
      {
        "ts": 1774407600000,
        "open": 4583.285,
        "high": 4585.905,
        "low": 4571.548,
        "close": 4575.135
      },
      {
        "ts": 1774409400000,
        "open": 4575.165,
        "high": 4577.408,
        "low": 4567.258,
        "close": 4569.738
      },
      {
        "ts": 1774411200000,
        "open": 4569.595,
        "high": 4574.265,
        "low": 4565.295,
        "close": 4573.985
      },
      {
        "ts": 1774413000000,
        "open": 4573.905,
        "high": 4574.385,
        "low": 4565.865,
        "close": 4572.248
      },
      {
        "ts": 1774414800000,
        "open": 4572.495,
        "high": 4573.295,
        "low": 4553.355,
        "close": 4554.345
      },
      {
        "ts": 1774416600000,
        "open": 4554.315,
        "high": 4566.555,
        "low": 4548.898,
        "close": 4555.215
      },
      {
        "ts": 1774418400000,
        "open": 4555.235,
        "high": 4556.655,
        "low": 4532.668,
        "close": 4550.295
      },
      {
        "ts": 1774420200000,
        "open": 4550.305,
        "high": 4556.505,
        "low": 4543.065,
        "close": 4545.405
      },
      {
        "ts": 1774422000000,
        "open": 4545.365,
        "high": 4562.915,
        "low": 4544.555,
        "close": 4560.795
      },
      {
        "ts": 1774423800000,
        "open": 4560.855,
        "high": 4560.855,
        "low": 4536.548,
        "close": 4539.065
      },
      {
        "ts": 1774425600000,
        "open": 4539.135,
        "high": 4567.475,
        "low": 4535.428,
        "close": 4565.445
      }
    ],
    "yDomain": [
      4301,
      4599
    ]
  },
  "horizons": [
    {
      "horizon": 1,
      "hours": 4,
      "predictedClose": 4577.961999976752,
      "lowerClose": 3849.1851481744857,
      "upperClose": 5444.720185302222,
      "uncertainty": 0.17339244484901428,
      "expectedReturnPct": 2.750287570248666,
      "actualClose": 4553.105,
      "actualReturnPct": 2.1923834426569755
    },
    {
      "horizon": 3,
      "hours": 12,
      "predictedClose": 4322.094800221551,
      "lowerClose": 3575.827444012347,
      "upperClose": 5224.1065192847345,
      "uncertainty": 0.18954358994960785,
      "expectedReturnPct": -2.9925360606103624,
      "actualClose": 4565.445,
      "actualReturnPct": 2.4693491642211463
    }
  ],
  "metrics": {
    "history": [
      {
        "epoch": 1,
        "trainTotal": -0.17384633846407713,
        "validationTotal": -0.20828304393216968,
        "trainReturn": -1.2009019509766452,
        "validationReturn": -1.4769304171204567,
        "trainProfit": -0.000015244896651667603,
        "validationProfit": 0.005546296546526719,
        "trainLogWealth": 0.000011625581562437345,
        "validationLogWealth": -0.004628615148249082
      },
      {
        "epoch": 2,
        "trainTotal": -0.2078313524148954,
        "validationTotal": -0.35008459724485874,
        "trainReturn": -1.4310661577439123,
        "validationReturn": -2.330749850720167,
        "trainProfit": 0.0022992808036326816,
        "validationProfit": -0.006673667994846255,
        "trainLogWealth": -0.0019176994946480922,
        "validationLogWealth": 0.0055440881112645
      },
      {
        "epoch": 3,
        "trainTotal": -0.2770312761584687,
        "validationTotal": -0.34718573559075594,
        "trainReturn": -1.867960577787355,
        "validationReturn": -2.3814932480454445,
        "trainProfit": 0.0002447143098108018,
        "validationProfit": 0.0030166111046128208,
        "trainLogWealth": -0.0002053843906647784,
        "validationLogWealth": -0.0025217544762199395
      },
      {
        "epoch": 4,
        "trainTotal": -0.32966509120639903,
        "validationTotal": -0.30740861978847533,
        "trainReturn": -2.2196054555648983,
        "validationReturn": -2.097516428679228,
        "trainProfit": 0.0006615546788297668,
        "validationProfit": 0.002208723452213235,
        "trainLogWealth": -0.0005536363031180457,
        "validationLogWealth": -0.0018489547921944904
      },
      {
        "epoch": 5,
        "trainTotal": -0.31674512793389403,
        "validationTotal": -0.018406827934086323,
        "trainReturn": -2.1209571181341658,
        "validationReturn": -0.16474630497395992,
        "trainProfit": -0.0007546918409212777,
        "validationProfit": 0.0026345670626142237,
        "trainLogWealth": 0.0006272067416160613,
        "validationLogWealth": -0.0022069988813200325
      },
      {
        "epoch": 6,
        "trainTotal": -0.2811016014401707,
        "validationTotal": -0.392638826277107,
        "trainReturn": -1.8945233821868896,
        "validationReturn": -2.585844613611698,
        "trainProfit": 0.000878538271867311,
        "validationProfit": -0.008777150441801496,
        "trainLogWealth": -0.0007340722907027284,
        "validationLogWealth": 0.007298988458956046
      }
    ],
    "validation": {
      "averageLogWealth": 0.00430597409890736,
      "realizedPnlPerAnchor": 0.004429503809889926,
      "cvarTailLoss": 0.021612780168652534,
      "noTradeBandHitRate": 0,
      "shapeGateUsage": 0.48368864227086306,
      "expertEntropy": 0.14246521890163422,
      "muCalibration": 0.09901334740987168,
      "sigmaCalibration": 0.05038660046955356,
      "directionalAccuracy": 0.71875,
      "projectValueScore": 0.5711067832502575,
      "exactSmoothHorizonAgreement": 0.84375,
      "exactSmoothNoTradeAgreement": 1,
      "exactSmoothPositionMae": 0.2989177416440315,
      "exactSmoothUtilityRegret": 0.0070845208398817375,
      "logWealthClampHitRate": 0,
      "stateResetMode": "carry_on",
      "turnover": 8.776042206270933,
      "maxDrawdown": 0.05190163901661479,
      "utilityScore": 0.6694646927362589
    }
  },
  "narrative": {
    "title": "横ばいです。",
    "summary": "短期判断はポジション調整です。 4時間先の予測値は 4,578 です。",
    "bullets": [
      "変化率は 2.75%、不確実性は 0.1734 です。",
      "予測幅は 3,849 - 5,445 です。",
      "policy score は 0.001、強さは 0.18 です。"
    ],
    "segments": [
      {
        "title": "4時間→12時間",
        "summary": "やや下向きます。",
        "fromStep": 1,
        "toStep": 3
      }
    ]
  }
}